zylo/__init__.py
zylo/components/__init__.py
zylo/components/blueprint.py
zylo/components/sessions.py
zylo/contrib/BaseModal.py
zylo/contrib/__init__.py
zylo/contrib/utils/__init__.py
zylo/contrib/utils/limiter.py
zylo/core/__init__.py
zylo/core/branch.py
zylo/mail/__init__.py
zylo/mail/zylo_mailer.py
zylo/security/JwT.py
zylo/security/__init__.py
zylo/security/chiper.py
zylo-2.0.7.dist-info/METADATA
zylo-2.0.7.dist-info/WHEEL
zylo-2.0.7.dist-info/top_level.txt
zylo-2.0.7.dist-info/RECORD
