Metadata-Version: 2.1
Name: zylo
Version: 2.0.7
Summary: A lightweight web framework made with love
Home-page: https://github.com/E491K7/zylo
Author: Pawan kumar
Author-email: control@vvfin.in
Classifier: Development Status :: 5 - Production/Stable
Classifier: License :: OSI Approved :: MIT License
Classifier: Programming Language :: Python :: 3
Classifier: Programming Language :: Python :: 3.6
Classifier: Programming Language :: Python :: 3.7
Classifier: Programming Language :: Python :: 3.8
Classifier: Programming Language :: Python :: 3.9
Requires-Dist: werkzeug
Requires-Dist: jinja2
Requires-Dist: cryptography
Requires-Dist: zylo-admin
Requires-Dist: itsdangerous
